pygent/__init__.py
pygent/__main__.py
pygent/agent.py
pygent/agent_presets.py
pygent/cli.py
pygent/commands.py
pygent/config.py
pygent/errors.py
pygent/fastapi_app.py
pygent/models.py
pygent/openai_compat.py
pygent/persona.py
pygent/prompt_library.py
pygent/py.typed
pygent/runtime.py
pygent/session.py
pygent/system_message.py
pygent/task_manager.py
pygent/task_tools.py
pygent/tools.py
pygent/ui.py
pygent-0.4.2.dist-info/licenses/LICENSE
pygent-0.4.2.dist-info/METADATA
pygent-0.4.2.dist-info/WHEEL
pygent-0.4.2.dist-info/entry_points.txt
pygent-0.4.2.dist-info/top_level.txt
pygent-0.4.2.dist-info/RECORD
