Metadata-Version: 2.4
Name: pygent
Version: 0.4.2
Summary: Pygent is a minimalist coding assistant that runs commands in a Docker container when available and falls back to local execution.
Author-email: Mariano Chaves <mchaves.software@gmail.com>
Project-URL: Documentation, https://pygent-ai.com
Project-URL: Repository, https://github.com/marianochaves/pygent
Requires-Python: >=3.9
License-File: LICENSE
Requires-Dist: rich>=13.7.0
Requires-Dist: openai>=1.0.0
Requires-Dist: tomli; python_version < "3.11"
Requires-Dist: typer>=0.9.0
Requires-Dist: questionary>=2.0.1
Provides-Extra: test
Requires-Dist: pytest; extra == "test"
Provides-Extra: docs
Requires-Dist: mkdocs; extra == "docs"
Requires-Dist: mkdocs-material; extra == "docs"
Requires-Dist: mkdocstrings[python]; extra == "docs"
Provides-Extra: docker
Requires-Dist: docker>=7.0.0; extra == "docker"
Provides-Extra: ui
Requires-Dist: gradio; extra == "ui"
Provides-Extra: server
Requires-Dist: fastapi; extra == "server"
Requires-Dist: uvicorn; extra == "server"
Dynamic: license-file
